recursereader/__init__.py
recursereader/recursereader.py
recursereader-0.0.1.dist-info/METADATA
recursereader-0.0.1.dist-info/WHEEL
recursereader-0.0.1.dist-info/entry_points.txt
recursereader-0.0.1.dist-info/top_level.txt
recursereader-0.0.1.dist-info/RECORD
