Metadata-Version: 2.1
Name: recursereader
Version: 0.0.1
Summary: Command-line tool for recursively traversing directories to print file paths and their contents. 
Author-email: Vasilii Platon <vasia.platon@gmail.com>
Project-URL: Homepage, https://github.com/vasiaplaton/recurse-reader
Project-URL: Issues, https://github.com/vasiaplaton/recurse-reader/issues
Classifier: Programming Language :: Python :: 3
Classifier: License :: OSI Approved :: MIT License
Classifier: Operating System :: OS Independent
Requires-Python: >=3.8
